riordinato/__init__.py
riordinato/cli.py
riordinato/cli_utils.py
riordinato/exceptions.py
riordinato/files.py
riordinato-1.7.4.dist-info/entry_points.txt
riordinato-1.7.4.dist-info/WHEEL
riordinato-1.7.4.dist-info/METADATA
riordinato-1.7.4.dist-info/RECORD
