Metadata-Version: 2.1
Name: riordinato
Version: 1.7.4
Summary: organize your files with prefixes
Home-page: https://github.com/DAN-pix/Riordinato
License: MIT
Keywords: organize,riordinato,prefixes,dir
Author: Dan-
Author-email: misternutel@gmail.com
Requires-Python: >=3.8,<4.0
Classifier: License :: OSI Approved :: MIT License
Classifier: Programming Language :: Python :: 3
Classifier: Programming Language :: Python :: 3.8
Classifier: Programming Language :: Python :: 3.9
Requires-Dist: click (>=7.1.2,<8.0.0)
Requires-Dist: typer (>=0.3.2,<0.4.0)
Project-URL: Repository, https://github.com/DAN-pix/Riordinato
